wf_google_workspace_api_client/__init__.py
wf_google_workspace_api_client/api/__init__.py
wf_google_workspace_api_client/api/client.py
wf_google_workspace_api_client/const.py
wf_google_workspace_api_client/models/user.py
wf_google_workspace_api_client/models/watch.py
wf_google_workspace_api_client-1.0.2.dist-info/LICENSE
wf_google_workspace_api_client-1.0.2.dist-info/METADATA
wf_google_workspace_api_client-1.0.2.dist-info/WHEEL
wf_google_workspace_api_client-1.0.2.dist-info/RECORD
